alphazero_game_env/__init__.py
alphazero_game_env/GoGame/Agent.py
alphazero_game_env/GoGame/AlphaZeroNetwork.py
alphazero_game_env/GoGame/GoGame.py
alphazero_game_env/GoGame/MCTS.py
alphazero_game_env/GoGame/SemiSelfPlay.py
alphazero_game_env/GoGame/SimpleGame.py
alphazero_game_env/GoGame/__init__.py
alphazero_game_env/SimpleGomoku/Gomoku.py
alphazero_game_env/SimpleGomoku/__init__.py
alphazero_game_env/SimpleOthello/__init__.py
alphazero_game_env/SimpleOthello/agent.py
alphazero_game_env/SimpleOthello/config.py
alphazero_game_env/SimpleOthello/env.py
alphazero_game_env/SimpleOthello/humanPlayer.py
alphazero_game_env/SimpleOthello/main.py
alphazero_game_env/SimpleOthello/othello.py
alphazero_game_env/SimpleOthello/randomPlayer.py
alphazero_game_env/TicTacToe/TicTacToe.py
alphazero_game_env/TicTacToe/__init__.py
AlphaZero_GameEnv-1.1.4.0.dist-info/METADATA
AlphaZero_GameEnv-1.1.4.0.dist-info/WHEEL
AlphaZero_GameEnv-1.1.4.0.dist-info/top_level.txt
AlphaZero_GameEnv-1.1.4.0.dist-info/RECORD
