Metadata-Version: 2.1
Name: AlphaZero-GameEnv
Version: 1.1.4.0
Summary: alphazero_game_env
Home-page: https://github.com/Michi-123/AlphaZeroGameEnv
Author: M.Uchiyama
License: MIT
Keywords: gogame tic-tac-toe othello gomoku
Classifier: License :: OSI Approved :: MIT License
Classifier: Programming Language :: Python :: 3.8
